mapsmx/__init__.py
mapsmx/mapsmx.py
mapsmx/utils.py
mapsmx/geo/ent.zip
mapsmx/geo/mun.zip
mapsmx/tests/__init__.py
mapsmx/tests/test_get_geo.py
mapsmx-0.0.3.dist-info/LICENSE
mapsmx-0.0.3.dist-info/METADATA
mapsmx-0.0.3.dist-info/WHEEL
mapsmx-0.0.3.dist-info/top_level.txt
mapsmx-0.0.3.dist-info/RECORD
