Metadata-Version: 2.1
Name: mapsmx
Version: 0.0.3
Summary: Create maps of México easily with Python.
Home-page: https://github.com/FedericoGarza/mapsmx
Author: Federico Garza
Author-email: fede.garza.ramirez@gmail.com
License: UNKNOWN
Platform: UNKNOWN
Classifier: Programming Language :: Python :: 3
Classifier: License :: OSI Approved :: MIT License
Classifier: Operating System :: OS Independent
Requires-Python: >=3.5
Requires-Dist: geopandas (>=0.7.0)
